multiwebcam/__init__.py
multiwebcam/__main__.py
multiwebcam/_version.py
multiwebcam/cameras/camera.py
multiwebcam/cameras/live_stream.py
multiwebcam/cameras/synchronizer.py
multiwebcam/configurator.py
multiwebcam/gui/camera_config_dialogue.py
multiwebcam/gui/camera_management/camera_display_widget.py
multiwebcam/gui/camera_management/multiplayback_widget.py
multiwebcam/gui/camera_management/playback_widget.py
multiwebcam/gui/frame_dictionary_emitter.py
multiwebcam/gui/frame_emitter.py
multiwebcam/gui/icons/mwc_logo.png
multiwebcam/gui/icons/mwc_logo.svg
multiwebcam/gui/icons/mwc_logo_big.png
multiwebcam/gui/icons/rotate-camera-left.svg
multiwebcam/gui/icons/rotate-camera-right.svg
multiwebcam/gui/icons/tri-cam.svg
multiwebcam/gui/icons/video-camera.svg
multiwebcam/gui/log_widget.py
multiwebcam/gui/main_widget.py
multiwebcam/gui/multicamera_widget.py
multiwebcam/gui/single_camera_widget.py
multiwebcam/gui/synched_frames_display.py
multiwebcam/gui/workspace_widget.py
multiwebcam/helper.py
multiwebcam/interface.py
multiwebcam/logger.py
multiwebcam/recording/multi_video_recorder.py
multiwebcam/recording/recorded_stream.py
multiwebcam/recording/single_video_recorder.py
multiwebcam/session/session.py
multiwebcam-0.1.2.dist-info/entry_points.txt
multiwebcam-0.1.2.dist-info/LICENSE
multiwebcam-0.1.2.dist-info/METADATA
multiwebcam-0.1.2.dist-info/WHEEL
multiwebcam-0.1.2.dist-info/RECORD
