Metadata-Version: 2.1
Name: multiwebcam
Version: 0.1.2
Summary: Record synchronized webcam footage
License: BSD-2-Clause
Author: Mac Prible
Author-email: prible@gmail.com
Requires-Python: >=3.10,<3.13
Classifier: License :: OSI Approved :: BSD License
Classifier: Programming Language :: Python :: 3
Classifier: Programming Language :: Python :: 3.10
Classifier: Programming Language :: Python :: 3.11
Classifier: Programming Language :: Python :: 3.12
Requires-Dist: PySide6 (>=6.6.1,<7.0.0)
Requires-Dist: opencv-contrib-python (>=4.8.1.78,<5.0.0.0)
Requires-Dist: pandas (>=2.1.4,<3.0.0)
Requires-Dist: rtoml (>=0.9.0,<0.10.0)
